{
  "project_info": {
    "project_number": "774522849083",
    "project_id": "feedz-f24bc",
    "storage_bucket": "feedz-f24bc.appspot.com"
  },
  "client": [
    {
      "client_info": {
        "mobilesdk_app_id": "1:774522849083:android:ae216cc24bfe979c1bd91e",
        "android_client_info": {
          "package_name": "com.life4.flowpod"
        }
      },
      "oauth_client": [
        {
          "client_id": "774522849083-8j04n99scjak3dktssnqbm7a9j9d1fq1.apps.googleusercontent.com",
          "client_type": 1,
          "android_info": {
            "package_name": "com.life4.flowpod",
            "certificate_hash": "373b808a0f3e8e4e119d8c8de5891c5bdb7bf85a"
          }
        },
        {
          "client_id": "774522849083-rga8ro4lhbut739begn5aesosm5cn6hp.apps.googleusercontent.com",
          "client_type": 3
        }
      ],
      "api_key": [
        {
          "current_key": "AIzaSyAnvXiLT0hBiTIrlvioZtPmfLaWqhv9r_g"
        }
      ],
      "services": {
        "appinvite_service": {
          "other_platform_oauth_client": [
            {
              "client_id": "774522849083-rga8ro4lhbut739begn5aesosm5cn6hp.apps.googleusercontent.com",
              "client_type": 3
            }
          ]
        }
      }
    }
  ],
  "configuration_version": "1"
}